fin_calculate/__init__.py
fin_calculate/numericl_calc.py
fin_calculate-0.1.0.dist-info/METADATA
fin_calculate-0.1.0.dist-info/WHEEL
fin_calculate-0.1.0.dist-info/top_level.txt
fin_calculate-0.1.0.dist-info/RECORD
